wedgedriver/__init__.py
wedgedriver/aestools.py
wedgedriver/loggers.py
wedgedriver/rsatools.py
wedgedriver/utils.py
wedgedriver/xortools.py
wedgedriver/data/english_words.txt
wedgedriver-0.1.2.dist-info/LICENSE
wedgedriver-0.1.2.dist-info/METADATA
wedgedriver-0.1.2.dist-info/WHEEL
wedgedriver-0.1.2.dist-info/top_level.txt
wedgedriver-0.1.2.dist-info/RECORD
