Metadata-Version: 2.1
Name: wedgedriver
Version: 0.1.2
Summary: A collection of tools to break common cryptography weaknesses
Home-page: https://github.com/pietroferretti/wedgedriver
Author: Pietro Ferretti
Author-email: pietro.ferretti1@gmail.com
License: MIT
Project-URL: Source, https://github.com/pietroferretti/wedgedriver
Keywords: ctf security cryptography
Platform: UNKNOWN
Classifier: Development Status :: 3 - Alpha
Classifier: Programming Language :: Python :: 2
Classifier: Programming Language :: Python :: 2.7
Classifier: Programming Language :: Python :: 3
Classifier: Programming Language :: Python :: 3.4
Classifier: Programming Language :: Python :: 3.5
Classifier: Programming Language :: Python :: 3.6
Classifier: Programming Language :: Python :: 3.7
Classifier: License :: OSI Approved :: MIT License
Classifier: Operating System :: OS Independent
Classifier: Topic :: Security
Classifier: Topic :: Security :: Cryptography
Requires-Dist: six
Provides-Extra: rsa
Requires-Dist: gmpy; extra == 'rsa'
Provides-Extra: tests
Requires-Dist: pytest; extra == 'tests'
Requires-Dist: pycryptodome; extra == 'tests'
